pulso/__init__.py
pulso/api.py
pulso/cache.py
pulso/cache_backends.py
pulso/cli.py
pulso/config.py
pulso/core.py
pulso/domain.py
pulso/fetcher.py
pulso-0.1.2.dist-info/licenses/LICENSE
tests/__init__.py
tests/test_domain.py
tests/test_error_handling.py
pulso-0.1.2.dist-info/METADATA
pulso-0.1.2.dist-info/WHEEL
pulso-0.1.2.dist-info/entry_points.txt
pulso-0.1.2.dist-info/top_level.txt
pulso-0.1.2.dist-info/RECORD
