Metadata-Version: 2.4
Name: pulso
Version: 0.1.2
Summary: Pulso delivers stateful web fetching with cache, hashes, and domain-aware rules
Home-page: https://github.com/jhd3197/Pulso
Author: Juan Denis
Author-email: Juan Denis <juan@vene.co>
License: MIT
Project-URL: Homepage, https://github.com/jhd3197/pulso
Project-URL: Issues, https://github.com/jhd3197/pulso/issues
Classifier: Development Status :: 3 - Alpha
Classifier: Intended Audience :: Developers
Classifier: Topic :: Software Development :: Libraries :: Python Modules
Classifier: Topic :: Internet :: WWW/HTTP
Classifier: License :: OSI Approved :: MIT License
Classifier: Programming Language :: Python :: 3
Classifier: Programming Language :: Python :: 3.8
Classifier: Programming Language :: Python :: 3.9
Classifier: Programming Language :: Python :: 3.10
Classifier: Programming Language :: Python :: 3.11
Classifier: Programming Language :: Python :: 3.12
Requires-Python: >=3.8
License-File: LICENSE
Requires-Dist: requests>=2.31.0
Requires-Dist: playwright>=1.40.0
Requires-Dist: beautifulsoup4>=4.12.0
Requires-Dist: lxml>=4.9.0
Provides-Extra: dev
Requires-Dist: pytest>=7.4.0; extra == "dev"
Requires-Dist: pytest-cov>=4.1.0; extra == "dev"
Requires-Dist: black>=23.0.0; extra == "dev"
Requires-Dist: flake8>=6.0.0; extra == "dev"
Requires-Dist: mypy>=1.5.0; extra == "dev"
Provides-Extra: api
Requires-Dist: flask>=2.3.0; extra == "api"
Provides-Extra: redis
Requires-Dist: redis>=5.0.0; extra == "redis"
Provides-Extra: all
Requires-Dist: redis>=5.0.0; extra == "all"
Requires-Dist: flask>=2.3.0; extra == "all"
Dynamic: author
Dynamic: home-page
Dynamic: license-file
Dynamic: requires-python
